tempsave/__init__.py
tempsave/tempsave.py
tempsave-0.1.0.dist-info/METADATA
tempsave-0.1.0.dist-info/WHEEL
tempsave-0.1.0.dist-info/RECORD
