Metadata-Version: 2.4
Name: tempsave
Version: 0.1.0
Summary: A package for saving variables during development
Author-email: Dibya Ghosh <dibya@berkeley.edu>
Requires-Python: >=3.7
Requires-Dist: asttokens
Requires-Dist: executing
